LICENSE.MIT
MANIFEST.in
README
setup.py
src/django_softlayer/__init__.py
src/django_softlayer/models.py
src/django_softlayer/softlayer_storage.py
src/django_softlayer.egg-info/PKG-INFO
src/django_softlayer.egg-info/SOURCES.txt
src/django_softlayer.egg-info/dependency_links.txt
src/django_softlayer.egg-info/not-zip-safe
src/django_softlayer.egg-info/requires.txt
src/django_softlayer.egg-info/top_level.txt
src/django_softlayer/management/__init__.py
src/django_softlayer/management/commands/__init__.py
src/django_softlayer/management/commands/get_missing_files.py
src/django_softlayer/management/commands/syncstatic.py
src/django_softlayer/tests/__init__.py
src/django_softlayer/tests/tests.py
src/django_softlayer/tests/test_data/1.mp3