Metadata-Version: 1.1
Name: django-softlayer
Version: 0.2
Summary: Django storage for SoftLayer Cloud Storage
Home-page: https://github.com/Arpaso/django-softlayer
Author: Arpaso
Author-email: arvid@arpaso.com
License: UNKNOWN
Download-URL: https://github.com/Arpaso/django-softlayer/tarball/0.2
Keywords: django,softlayer,storage,cloudfiles
Platform: UNKNOWN
Classifier: Development Status :: 4 - Beta
Classifier: Framework :: Django
Classifier: Intended Audience :: Developers
Classifier: Intended Audience :: System Administrators
Classifier: Operating System :: OS Independent
Classifier: Topic :: Software Development
